nerfw/__init__.py
nerfw/nerfw.py
nerfw/game/__init__.py
nerfw/game/animation.py
nerfw/game/audio.py
nerfw/game/character.py
nerfw/game/choice.py
nerfw/game/game.py
nerfw/game/scene.py
nerfw/game/string_input.py
nerfw/game/unlock_scene.py
nerfw/helpers/__init__.py
nerfw/helpers/breaker.py
nerfw/helpers/db_handler.py
nerfw/helpers/deconstructor.py
nerfw/helpers/img_handler.py
nerfw/helpers/input_handler.py
nerfw/helpers/logger.py
nerfw/helpers/login_base.py
nerfw/helpers/recorder.py
nerfw/helpers/errors/__init__.py
nerfw/helpers/errors/character_not_found.py
nerfw/helpers/errors/function_not_found.py
nerfw/helpers/errors/password_mismatch.py
nerfw/helpers/errors/unsupported_login_method.py
nerfw/helpers/errors/user_already_registered.py
nerfw/helpers/errors/user_doesnt_exist.py
nerfw/helpers/errors/user_not_allowed.py
nerfw/helpers/errors/wrong_naming.py
nerfw/server/__init__.py
nerfw/server/gallery.py
nerfw/server/login_default.py
nerfw/server/login_github.py
nerfw/server/login_patreon.py
nerfw/server/password_manager.py
nerfw/server/require_token.py
nerfw/server/saves_handler.py
nerfw/server/server.py
nerfw/server/token_handler.py
nerfw/server/wrapper.py
nerfw/server/build/asset-manifest.json
nerfw/server/build/favicon.ico
nerfw/server/build/index.html
nerfw/server/build/logo192.png
nerfw/server/build/logo512.png
nerfw/server/build/manifest.json
nerfw/server/build/robots.txt
nerfw/server/build/static/css/main.d6aa7cc8.css
nerfw/server/build/static/css/main.d6aa7cc8.css.map
nerfw/server/build/static/js/453.5751972e.chunk.js
nerfw/server/build/static/js/453.5751972e.chunk.js.map
nerfw/server/build/static/js/main.64691e94.js
nerfw/server/build/static/js/main.64691e94.js.LICENSE.txt
nerfw/server/build/static/js/main.64691e94.js.map
nerfw/server/build/static/media/PATREON_SYMBOL_1_WHITE_RGB.17310609229eef2df4c7c31535ee8843.svg
nerfw/server/build/static/media/github-mark-white.97ed8e7eef60d61ca469881dd6f34511.svg
nerfw-0.1.8.dist-info/LICENSE
nerfw-0.1.8.dist-info/METADATA
nerfw-0.1.8.dist-info/WHEEL
nerfw-0.1.8.dist-info/top_level.txt
nerfw-0.1.8.dist-info/RECORD
