Metadata-Version: 2.1
Name: nerfw
Version: 0.1.8
Summary: Framework for creation of web based visual novels
Author-email: Nergan <noname.nosurname2016@yandex.ru>
License: MIT License
Project-URL: homepage, https://github.com/Nergan123/NerFW/tree/main
Project-URL: repository, https://github.com/Nergan123/NerFW/tree/main
Keywords: flask,visual,novel,web
Classifier: Framework :: Flask
Classifier: Programming Language :: Python :: 3
Classifier: Intended Audience :: Developers
Classifier: License :: OSI Approved :: MIT License
Classifier: Operating System :: OS Independent
Classifier: Programming Language :: Python :: 3
Classifier: Programming Language :: Python :: 3.10
Classifier: Programming Language :: Python :: 3.11
Classifier: Topic :: Games/Entertainment
Classifier: Topic :: Games/Entertainment :: Role-Playing
Classifier: Topic :: Internet :: WWW/HTTP :: HTTP Servers
Classifier: Topic :: Software Development :: Libraries :: Python Modules
Requires-Python: >=3.10
License-File: LICENSE
Requires-Dist: python-dotenv
Requires-Dist: flask
Requires-Dist: pyjwt
Requires-Dist: authlib
Requires-Dist: requests
Requires-Dist: patreon
Requires-Dist: pillow
Provides-Extra: dev
Requires-Dist: black ; extra == 'dev'
Requires-Dist: pylint ; extra == 'dev'
Requires-Dist: pytest ; extra == 'dev'
Requires-Dist: sphinx ; extra == 'dev'
Requires-Dist: sphinx-rtd-theme ; extra == 'dev'
Requires-Dist: myst-parser ; extra == 'dev'
